odoo/addons/account_billing/README.rst
odoo/addons/account_billing/__init__.py
odoo/addons/account_billing/__manifest__.py
odoo/addons/account_billing/data/account_billing_sequence.xml
odoo/addons/account_billing/data/account_invoice.xml
odoo/addons/account_billing/i18n/account_billing.pot
odoo/addons/account_billing/i18n/de.po
odoo/addons/account_billing/i18n/es.po
odoo/addons/account_billing/models/__init__.py
odoo/addons/account_billing/models/account_billing.py
odoo/addons/account_billing/models/account_invoice.py
odoo/addons/account_billing/readme/CONTRIBUTORS.rst
odoo/addons/account_billing/readme/DESCRIPTION.rst
odoo/addons/account_billing/readme/USAGE.rst
odoo/addons/account_billing/report/report.xml
odoo/addons/account_billing/report/report_billing.xml
odoo/addons/account_billing/security/ir.model.access.csv
odoo/addons/account_billing/static/description/icon.png
odoo/addons/account_billing/static/description/index.html
odoo/addons/account_billing/static/src/img/icon.png
odoo/addons/account_billing/tests/__init__.py
odoo/addons/account_billing/tests/test_account_billing.py
odoo/addons/account_billing/views/account_billing.xml
odoo/addons/account_billing/views/account_invoice_view.xml
odoo12_addon_account_billing-12.0.1.0.1.dist-info/METADATA
odoo12_addon_account_billing-12.0.1.0.1.dist-info/WHEEL
odoo12_addon_account_billing-12.0.1.0.1.dist-info/top_level.txt
odoo12_addon_account_billing-12.0.1.0.1.dist-info/RECORD
